ScoreDrivenBOCPD/__init__.py
ScoreDrivenBOCPD/data.py
ScoreDrivenBOCPD/prob_model.py
ScoreDrivenBOCPD/sd_ar.py
ScoreDrivenBOCPD/sd_bocpd.py
ScoreDrivenBOCPD/untitled1.py
ScoreDrivenBOCPD-0.1.8.dist-info/LICENSE
ScoreDrivenBOCPD-0.1.8.dist-info/METADATA
ScoreDrivenBOCPD-0.1.8.dist-info/WHEEL
ScoreDrivenBOCPD-0.1.8.dist-info/top_level.txt
ScoreDrivenBOCPD-0.1.8.dist-info/RECORD
