Metadata-Version: 2.1
Name: ScoreDrivenBOCPD
Version: 0.1.8
Summary: A Score-Driven Bayesian Online Change-Point Detection Package
Home-page: https://gitlab.com/YvTsak/ScoreDrivenBOCPD
Author: Yvonni Tsaknaki
Author-email: mathematyvian@gmail.com
License: MIT License
Requires-Dist: numpy
Requires-Dist: pandas
Requires-Dist: matplotlib
Requires-Dist: scipy
